cloudprober/external/server_pb2.py
cloudprober/external/serverutils.py
cloudprober_serverutils-0.13.9.post62.dist-info/METADATA
cloudprober_serverutils-0.13.9.post62.dist-info/WHEEL
cloudprober_serverutils-0.13.9.post62.dist-info/top_level.txt
cloudprober_serverutils-0.13.9.post62.dist-info/RECORD
