Metadata-Version: 2.4
Name: cloudprober-serverutils
Version: 0.13.9.post62
Summary: Package for Cloudprober's external probe's serverutils
Project-URL: Homepage, https://cloudprober.org
Project-URL: Repository, https://github.com/cloudprober/cloudprober
Requires-Dist: protobuf
